{
  "generatedAt": "2026-06-30T10:13:11.679Z",
  "source": "https://identity-api.dimo.zone/query",
  "stats": {
    "generatedAt": "2026-06-30T10:13:11.679Z",
    "observed": 158149,
    "aftermarketDevices": 40622,
    "syntheticDevices": 31402,
    "backedDevices": 72024,
    "unbackedVehicles": 86125,
    "hardwarePct": 0.25685903799581405,
    "syntheticPct": 0.19855958621300165,
    "backedPct": 0.45541862420881574,
    "unbackedPct": 0.5445813757911843
  },
  "prevStats": {
    "generatedAt": "2026-06-29T15:08:48.903Z",
    "observed": 158137,
    "aftermarketDevices": 40622,
    "syntheticDevices": 31402,
    "backedDevices": 72024,
    "unbackedVehicles": 86113,
    "hardwarePct": 0.25687852937642675,
    "syntheticPct": 0.19857465362312426,
    "backedPct": 0.455453182999551,
    "unbackedPct": 0.5445468170004489
  }
}